hgtk/__init__.py
hgtk/checker.py
hgtk/const.py
hgtk/exception.py
hgtk/josa.py
hgtk/letter.py
hgtk/text.py
hgtk-0.2.0.dist-info/LICENSE
hgtk-0.2.0.dist-info/METADATA
hgtk-0.2.0.dist-info/WHEEL
hgtk-0.2.0.dist-info/top_level.txt
hgtk-0.2.0.dist-info/RECORD
