Metadata-Version: 2.1
Name: hgtk
Version: 0.2.0
Summary: Toolkit for Hangul composing, decomposing and etc...
Home-page: https://github.com/bluedisk/hangul-toolkit
Author: Wonwoo, lee
Author-email: bluedisk@gmail.com
License: Apache 2.0
Keywords: hangul charactorjamo automada composing decomposing josa
Classifier: Development Status :: 4 - Beta
Classifier: Intended Audience :: Developers
Classifier: Topic :: Text Processing
Classifier: License :: OSI Approved :: Apache Software License
Classifier: Programming Language :: Python :: 2.7
Classifier: Programming Language :: Python :: 3.3
Classifier: Programming Language :: Python :: 3.4
Classifier: Programming Language :: Python :: 3.5
Classifier: Programming Language :: Python :: 3.6
Classifier: Programming Language :: Python :: 3.7
Classifier: Programming Language :: Python :: 3.8
Classifier: Programming Language :: Python :: 3.9
Classifier: Programming Language :: Python :: 3.10
Classifier: Programming Language :: Python :: 3.11
Classifier: Programming Language :: Python :: Implementation :: PyPy
License-File: LICENSE
